scidb/__init__.py
scidb/client/__init__.py
scidb/client/global_env.py
scidb/client/modules/__init__.py
scidb/client/modules/bucket.py
scidb/client/modules/data.py
scidb/client/modules/data_set.py
scidb/client/modules/database.py
scidb/client/modules/metadata.py
scidb/core/__init__.py
scidb/core/bucket.py
scidb/core/data.py
scidb/core/data_set.py
scidb/core/database.py
scidb/core/low/__init__.py
scidb/core/low/metadata.py
scidb/core/low/node.py
scidb/plugins/__init__.py
scidb/plugins/backup/__init__.py
scidb/plugins/backup/base/__init__.py
scidb/plugins/backup/base/backend.py
scidb/plugins/backup/base/backup_profile.py
scidb/plugins/backup/implementations/__init__.py
scidb/plugins/backup/implementations/local.py
scidb/plugins/backup/implementations/minio.py
scidb/plugins/sandbox/__init__.py
scidb/plugins/sandbox/sandbox.py
scidb/utils/__init__.py
scidb/utils/cleaner.py
scidb/utils/data_import.py
scidb/utils/extractor.py
scidb/utils/iteration.py
scidb/utils/migrator.py
scidb/utils/search.py
scidb/utils/walk.py
oxdc_scidb-0.2b5.dist-info/LICENSE
oxdc_scidb-0.2b5.dist-info/METADATA
oxdc_scidb-0.2b5.dist-info/WHEEL
oxdc_scidb-0.2b5.dist-info/top_level.txt
oxdc_scidb-0.2b5.dist-info/RECORD
