Metadata-Version: 2.1
Name: oxdc-scidb
Version: 0.2b5
Summary: A simple scientific database.
Home-page: https://github.com/oxdc/sci.db
Author: oxdc
Author-email: projaias@outlook.com
License: MIT License
Keywords: database,scientific database,data science
Platform: UNKNOWN
Requires-Dist: PyYAML
Requires-Dist: minio
Requires-Dist: urllib3
